Metadata-Version: 1.0
Name: distributions-LelandCurtis2
Version: 1.3
Summary: Gaussian distributions
Home-page: UNKNOWN
Author: Leland Curtis
Author-email: lelandcurtis88@gmail.com
License: UNKNOWN
Platform: UNKNOWN
